xarray_nanonis/NanonisBackendEntrypoint.py
xarray_nanonis/__init__.py
xarray_nanonis/nanonis.py
xarray_nanonis/utils.py
xarray_nanonis-2025.6.0.dist-info/licenses/LICENSE
xarray_nanonis-2025.6.0.dist-info/METADATA
xarray_nanonis-2025.6.0.dist-info/WHEEL
xarray_nanonis-2025.6.0.dist-info/entry_points.txt
xarray_nanonis-2025.6.0.dist-info/top_level.txt
xarray_nanonis-2025.6.0.dist-info/RECORD
