Metadata-Version: 2.4
Name: xarray-nanonis
Version: 2025.6.0
Summary: Extending xarray to read Nanonis files with coordinates and metadata
Author-email: Hao Zhang <zhanghao3859@hotmail.com>
Maintainer-email: Hao Zhang <zhanghao3859@hotmail.com>
License-Expression: MIT
Project-URL: Homepage, https://github.com/John3859/xarray-nanonis
Project-URL: Repository, https://github.com/John3859/xarray-nanonis
Project-URL: Documentation, https://github.com/John3859/xarray-nanonis#readme
Project-URL: Bug Tracker, https://github.com/John3859/xarray-nanonis/issues
Keywords: xarray,nanonis,scanning probe microscopy,SPM,STM,AFM,data analysis
Classifier: Development Status :: 4 - Beta
Classifier: Intended Audience :: Science/Research
Classifier: Operating System :: OS Independent
Classifier: Programming Language :: Python :: 3
Classifier: Programming Language :: Python :: 3.9
Classifier: Programming Language :: Python :: 3.10
Classifier: Programming Language :: Python :: 3.11
Classifier: Programming Language :: Python :: 3.12
Classifier: Programming Language :: Python :: 3.13
Classifier: Topic :: Scientific/Engineering :: Physics
Classifier: Topic :: Scientific/Engineering :: Visualization
Requires-Python: >=3.9
License-File: LICENSE
Requires-Dist: numpy>=1.20.0
Requires-Dist: xarray>=0.18.0
Requires-Dist: pandas>=1.3.0
Dynamic: license-file
